{"route_release_id": 51, "route_release_revision": 3, "route_algorithm_version": 10.2, "results": [{"description": "total", "demographic": "Adults 15-34 (16)", "granular_audience": "All Adults (1)", "target_month": 3, "figures": {"impacts": "611.6310045115", "impacts_pedestrian": "388.9144967448", "impacts_vehicular": "222.7165077667", "gross_rating_points": "3.7339540302", "reach": "217.8454495095", "reach_pedestrian": "138.8816757466", "reach_vehicular": "99.1641852158", "average_frequency": "2.8076372763", "rag_status": "green"}, "metrics": {"total_frames": 100, "total_dynamic_frames": 100, "total_contacts": 326438, "total_actual_contacts": 204074, "total_respondents": 5857, "total_actual_respondents": 351}}, {"description": "grouping", "demographic": "Adults 15-34 (16)", "granular_audience": "All Adults (1)", "target_month": 3, "environment": "20", "figures": {"impacts": "611.6310045115", "impacts_pedestrian": "388.9144967448", "impacts_vehicular": "222.7165077667", "gross_rating_points": "3.7339540302", "reach": "217.8454495095", "reach_pedestrian": "138.8816757466", "reach_vehicular": "99.1641852158", "average_frequency": "2.8076372763", "rag_status": "green"}, "metrics": {"total_frames": 100, "total_dynamic_frames": 100, "total_contacts": 326438, "total_actual_contacts": 204074, "total_respondents": 5857, "total_actual_respondents": 351}}], "total_processing_time": 3424, "processed_datetime": "2025-07-28 17:01:51"}